verilog/ALU/ALU.srcs/sources_1/new/alu.v
`timescale 1ns / 1ps
//////////////////////////////////////////////////////////////////////////////////
// Company: 
// Engineer: 
// 
// Create Date: 15.03.2026 21:52:30
// Design Name: 
// Module Name: alu
// Project Name: 
// Target Devices: 
// Tool Versions: 
// Description: 
// 
// Dependencies: 
// 
// Revision:
// Revision 0.01 - File Created
// Additional Comments:
// 
//////////////////////////////////////////////////////////////////////////////////


module alu(
    input [2:0] A,
    input [2:0] B,
    input [2:0] sel,
    output reg [2:0] Y
);

always @(*) begin
    case(sel)

        3'b000: Y = A + B;        // ADD

        3'b001: Y = A - B;        // SUB

        3'b010: Y = A & B;        // AND

        3'b011: Y = A | B;        // OR

        3'b100: Y = A ^ B;        // XOR

        3'b101: Y = ~(A & B);     // NAND

        3'b110: Y = ~(A | B);     // NOR

        3'b111: Y = ~A;           // NOT A

        default: Y = 3'b000;

    endcase
end

endmodule

verilog/ALU/ALU.srcs/sources_1/new/alu_tb.v
`timescale 1ns / 1ps
//////////////////////////////////////////////////////////////////////////////////
// Company: 
// Engineer: 
// 
// Create Date: 16.03.2026 22:25:25
// Design Name: 
// Module Name: alu_tb
// Project Name: 
// Target Devices: 
// Tool Versions: 
// Description: 
// 
// Dependencies: 
// 
// Revision:
// Revision 0.01 - File Created
// Additional Comments:
// 
//////////////////////////////////////////////////////////////////////////////////


module alu_tb;

reg [2:0] A, B;
reg [2:0] sel;
wire [2:0] Y;

alu uut(A,B,sel,Y);

initial begin

$dumpfile("alu.vcd");
$dumpvars(0, alu_tb);

A = 3'b101; B = 3'b010;

sel = 3'b000; #1;
sel = 3'b001; #1;
sel = 3'b010; #1;
sel = 3'b011; #1;
sel = 3'b100; #1;
sel = 3'b101; #1;
sel = 3'b110; #1;
sel = 3'b111; #1;

$finish;

end

endmodule

verilog/ALU/ALU.sim/sim_1/behav/xsim/alu.vcd
$date
   Mon Mar 16 22:43:27 2026
$end
$version
  2018.2
$end
$timescale
  1ps
$end
$scope module alu_tb $end
$var reg 3 ! A [2:0] $end
$var reg 3 " B [2:0] $end
$var reg 3 # sel [2:0] $end
$var wire 3 $ Y [2:0] $end
$scope module uut $end
$var wire 3 % A [2:0] $end
$var wire 3 & B [2:0] $end
$var wire 3 ' sel [2:0] $end
$var reg 3 ( Y [2:0] $end
$upscope $end
$upscope $end
$enddefinitions $end
#0
$dumpvars
b101 !
b10 "
b0 #
b111 $
b101 %
b10 &
b0 '
b111 (
$end
#1000
b1 #
b11 $
b1 '
b11 (
#2000
b10 #
b0 $
b10 '
b0 (
#3000
b11 #
b111 $
b11 '
b111 (
#4000
b100 #
b100 '
b111 (
#5000
b101 #
b101 '
b111 (
#6000
b110 #
b0 $
b110 '
b0 (
#7000
b111 #
b10 $
b111 '
b10 (
